Metadata-Version: 1.1
Name: url
Version: 0.1.1
Summary: URL Parsing
Home-page: http://github.com/seomoz/url-py
Author: Dan Lecocq
Author-email: dan@seomoz.org
License: MIT
Platform: Posix; MacOS X
Classifier: License :: OSI Approved :: MIT License
Classifier: Development Status :: 3 - Alpha
Classifier: Environment :: Web Environment
Classifier: Intended Audience :: Developers
Classifier: Topic :: Internet :: WWW/HTTP
Requires: publicsuffix
